pipext/__init__.py
pipext/main.py
pipext-0.2.3.dist-info/LICENSE
pipext-0.2.3.dist-info/METADATA
pipext-0.2.3.dist-info/WHEEL
pipext-0.2.3.dist-info/entry_points.txt
pipext-0.2.3.dist-info/top_level.txt
pipext-0.2.3.dist-info/RECORD
