Metadata-Version: 2.1
Name: pipext
Version: 0.2.3
Summary: An extended pip installer that updates requirements.txt
Home-page: UNKNOWN
Author: Usman Mukhtar
License: UNKNOWN
Platform: UNKNOWN
License-File: LICENSE
